aws_assume_role/__init__.py
aws_assume_role/accounts.py
aws_assume_role/aws-assume-role.py
aws_assume_role/aws_assume_role.py
aws_assume_role/version.py
aws_assume_role/writer.py
onelogin_aws_assume_role-1.10.1.dist-info/LICENSE
onelogin_aws_assume_role-1.10.1.dist-info/METADATA
onelogin_aws_assume_role-1.10.1.dist-info/WHEEL
onelogin_aws_assume_role-1.10.1.dist-info/entry_points.txt
onelogin_aws_assume_role-1.10.1.dist-info/top_level.txt
onelogin_aws_assume_role-1.10.1.dist-info/RECORD
