Metadata-Version: 2.1
Name: onelogin-aws-assume-role
Version: 1.10.1
Summary: Assume an AWS Role and get temporary credentials using OneLogin
Home-page: https://github.com/onelogin/onelogin-python-aws-assume-role
Author: OneLogin
Author-email: support@onelogin.com
License: MIT
Keywords: onelogin aws-assume-role
Classifier: Development Status :: 4 - Beta
Classifier: Intended Audience :: Developers
Classifier: Intended Audience :: System Administrators
Classifier: Operating System :: OS Independent
Classifier: Programming Language :: Python :: 2.7
Classifier: Programming Language :: Python :: 3.5
License-File: LICENSE
Requires-Dist: boto3 (>=1.7.84)
Requires-Dist: onelogin (==2.0.4)
Requires-Dist: pyyaml (>=5.1.2)
Requires-Dist: lxml
Provides-Extra: test
Requires-Dist: coverage (<6,>=3) ; extra == 'test'
Requires-Dist: pylint (<3,>=1) ; extra == 'test'
Requires-Dist: pep8 (<2,>=1) ; extra == 'test'
Requires-Dist: pyflakes (<3,>=1) ; extra == 'test'
